steamworkspy_RocketFriday/CHANGES.md
steamworkspy_RocketFriday/LICENSE
steamworkspy_RocketFriday/README.md
steamworkspy_RocketFriday/SteamworksPy64.dll
steamworkspy_RocketFriday/__init__.py
steamworkspy_RocketFriday/requirements.txt
steamworkspy_RocketFriday/setup.py
steamworkspy_RocketFriday/steam_api64.dll
steamworkspy_RocketFriday/steam_api64.lib
steamworkspy_RocketFriday/steamworks/__init__.py
steamworkspy_RocketFriday/steamworks/enums.py
steamworkspy_RocketFriday/steamworks/exceptions.py
steamworkspy_RocketFriday/steamworks/methods.py
steamworkspy_RocketFriday/steamworks/structs.py
steamworkspy_RocketFriday/steamworks/util.py
steamworkspy_RocketFriday/steamworks/interfaces/__init__.py
steamworkspy_RocketFriday/steamworks/interfaces/apps.py
steamworkspy_RocketFriday/steamworks/interfaces/friends.py
steamworkspy_RocketFriday/steamworks/interfaces/matchmaking.py
steamworkspy_RocketFriday/steamworks/interfaces/music.py
steamworkspy_RocketFriday/steamworks/interfaces/screenshots.py
steamworkspy_RocketFriday/steamworks/interfaces/users.py
steamworkspy_RocketFriday/steamworks/interfaces/userstats.py
steamworkspy_RocketFriday/steamworks/interfaces/utils.py
steamworkspy_RocketFriday/steamworks/interfaces/workshop.py
steamworkspy_rocketfriday-0.0.1.dist-info/METADATA
steamworkspy_rocketfriday-0.0.1.dist-info/WHEEL
steamworkspy_rocketfriday-0.0.1.dist-info/licenses/LICENSE
steamworkspy_rocketfriday-0.0.1.dist-info/RECORD
